nano_vllm_voxcpm-1.0.1.dist-info/licenses/LICENSE
nanovllm_voxcpm/__init__.py
nanovllm_voxcpm/_version.py
nanovllm_voxcpm/config.py
nanovllm_voxcpm/llm.py
nanovllm_voxcpm/engine/__init__.py
nanovllm_voxcpm/engine/block_manager.py
nanovllm_voxcpm/engine/llm_engine.py
nanovllm_voxcpm/engine/model_runner.py
nanovllm_voxcpm/engine/scheduler.py
nanovllm_voxcpm/engine/sequence.py
nanovllm_voxcpm/layers/__init__.py
nanovllm_voxcpm/layers/activation.py
nanovllm_voxcpm/layers/attention.py
nanovllm_voxcpm/layers/audio_vae.py
nanovllm_voxcpm/layers/embed_head.py
nanovllm_voxcpm/layers/layernorm.py
nanovllm_voxcpm/layers/linear.py
nanovllm_voxcpm/layers/lora.py
nanovllm_voxcpm/layers/rotary_embedding.py
nanovllm_voxcpm/layers/sampler.py
nanovllm_voxcpm/models/__init__.py
nanovllm_voxcpm/models/voxcpm/__init__.py
nanovllm_voxcpm/models/voxcpm/config.py
nanovllm_voxcpm/models/voxcpm/engine.py
nanovllm_voxcpm/models/voxcpm/model.py
nanovllm_voxcpm/models/voxcpm/runner.py
nanovllm_voxcpm/models/voxcpm/server.py
nanovllm_voxcpm/models/voxcpm/utils.py
nanovllm_voxcpm/utils/context.py
nanovllm_voxcpm/utils/loader.py
nanovllm_voxcpm/utils/torch_param.py
nano_vllm_voxcpm-1.0.1.dist-info/METADATA
nano_vllm_voxcpm-1.0.1.dist-info/WHEEL
nano_vllm_voxcpm-1.0.1.dist-info/top_level.txt
nano_vllm_voxcpm-1.0.1.dist-info/RECORD
