Metadata-Version: 2.4
Name: nano-vllm-voxcpm
Version: 1.0.1
Summary: VoxCPM inference engine based on Nano-vLLM
Author: Guoyang Zeng
Project-URL: Homepage, https://github.com/a710128/nanovllm-voxcpm
Classifier: License :: OSI Approved :: MIT License
Requires-Python: <3.13,>=3.10
License-File: LICENSE
Requires-Dist: torch!=2.6.*,>=2.5.0
Requires-Dist: triton>=3.0.0
Requires-Dist: transformers>=4.51.0
Requires-Dist: xxhash
Requires-Dist: torchaudio
Requires-Dist: tqdm
Requires-Dist: numpy
Requires-Dist: pydantic
Requires-Dist: flash-attn
Requires-Dist: soundfile>=0.13.1
Requires-Dist: torchcodec
Dynamic: license-file
